LICENSE.txt
MANIFEST.in
README.md
README.rst
setup.cfg
setup.py
crecomp/__init__.py
crecomp/communication.py
crecomp/component.py
crecomp/crecomp.py
crecomp/crecomp_utility.py
crecomp/scrp_lex.py
crecomp/scrp_parser.py
crecomp/scrp_yacc.py
crecomp/software.py
crecomp/userlogic.py
crecomp/verilog.py
crecomp.egg-info/PKG-INFO
crecomp.egg-info/SOURCES.txt
crecomp.egg-info/dependency_links.txt
crecomp.egg-info/entry_points.txt
crecomp.egg-info/requires.txt
crecomp.egg-info/top_level.txt
crecomp/ply/__init__.py
crecomp/ply/__init__.pyc
crecomp/ply/lex.py
crecomp/ply/lex.pyc
crecomp/ply/yacc.py
crecomp/ply/yacc.pyc
crecomp/template/__init__.py
crecomp/template/inst4top.jinja2
crecomp/template/ports.jinja2
crecomp/template/regwire.jinja2
crecomp/template/scrp.jinja2
crecomp/template/testbench.jinja2
crecomp/template/ulclassmodel.jinja2
crecomp/template/ulinstance.jinja2
crecomp/template/software/__init__.py
crecomp/template/software/bridge.py
crecomp/template/software/cpp_xillybus.jinja2
crecomp/template/software/cpp_xillybus_makefile.jinja2
crecomp/template/software/lib_cpp.h
crecomp/template/software/py_xillybus.jinja2
crecomp/template/software/ros_cmakelists.jinja2
crecomp/template/software/ros_msg.jinja2
crecomp/template/software/ros_package_xml.jinja2
crecomp/template/software/ros_scripts_py.jinja2
crecomp/template/software/ros_src.jinja2
crecomp/template/software/ros_test_comp_py.jinja2
crecomp/template/xillybus/__init__.py
crecomp/template/xillybus/xillybus_assign.jinja2
crecomp/template/xillybus/xillybus_enablectl.jinja2
crecomp/template/xillybus/xillybus_fifoinst.jinja2
crecomp/template/xillybus/xillybus_fsm.jinja2
crecomp/template/xillybus/xillybus_fsm_idle.jinja2
crecomp/template/xillybus/xillybus_fsm_pose.jinja2
crecomp/template/xillybus/xillybus_fsm_rcv.jinja2
crecomp/template/xillybus/xillybus_fsm_snd.jinja2
crecomp/template/xillybus/xillybus_inst4top.jinja2
crecomp/template/xillybus/xillybus_para_end.jinja2
crecomp/template/xillybus/xillybus_para_init_idle.jinja2
crecomp/template/xillybus/xillybus_para_pose.jinja2
crecomp/template/xillybus/xillybus_para_rcv.jinja2
crecomp/template/xillybus/xillybus_para_rcvend.jinja2
