Metadata-Version: 1.1
Name: crecomp
Version: 1.5.2
Summary: creator for Reconfigurable Component. Framework and Code generator for FPGA component
Home-page: https://github.com/kazuyamashi/cReComp.git
Author: Kazushi Yamashina
Author-email: kazuyamashi_at_gamil.com
License: new BSD
Keywords: FPGA,component,Verilog HDL
Platform: UNKNOWN
Classifier: Development Status :: 1 - Planning
Classifier: Environment :: Console
Classifier: Intended Audience :: Developers
Classifier: Natural Language :: English
Classifier: Operating System :: OS Independent
Classifier: Programming Language :: Python
Classifier: Topic :: Software Development :: Libraries :: Python Modules
Classifier: Topic :: Software Development :: Code Generators
Classifier: Topic :: System :: Hardware :: Hardware Drivers
Classifier: Topic :: Software Development :: Embedded Systems
Classifier: Topic :: Utilities
Classifier: License :: OSI Approved :: BSD License
